captcha2uploadcasesensitive/__init__.py
captcha2uploadcasesensitive/captcha2UploadCaseSensitive.py
captcha2uploadcasesensitive-0.2.dist-info/LICENSE.txt
captcha2uploadcasesensitive-0.2.dist-info/METADATA
captcha2uploadcasesensitive-0.2.dist-info/WHEEL
captcha2uploadcasesensitive-0.2.dist-info/top_level.txt
captcha2uploadcasesensitive-0.2.dist-info/RECORD
